pywebsocket/__init__.py
pywebsocket/custom_types.py
pywebsocket/exceptions.py
pywebsocket/server.py
pywebsocket-1.0.6.dist-info/LICENSE
pywebsocket-1.0.6.dist-info/METADATA
pywebsocket-1.0.6.dist-info/WHEEL
pywebsocket-1.0.6.dist-info/top_level.txt
pywebsocket-1.0.6.dist-info/RECORD
