Metadata-Version: 2.1
Name: pywebsocket
Version: 1.0.6
Summary: Websocket server written in Python.
Home-page: https://github.com/egebilecen/pywebsocket
Author: Ege Bilecen
License: UNKNOWN
Platform: UNKNOWN
Classifier: Programming Language :: Python :: 3
Classifier: Operating System :: OS Independent
Classifier: Intended Audience :: Developers
Classifier: Topic :: Software Development :: Libraries
Requires-Python: >=3.6
